mosaiks/__init__.py
mosaiks/checks.py
mosaiks/utils.py
mosaiks/featurize/__init__.py
mosaiks/featurize/create_features.py
mosaiks/featurize/model.py
mosaiks/fetch/__init__.py
mosaiks/fetch/images.py
mosaiks/fetch/stacs.py
mosaiks/pipeline/__init__.py
mosaiks/pipeline/parallel.py
mosaiks/pipeline/standard.py
mosaiks-1.0.0.dist-info/LICENSE
mosaiks-1.0.0.dist-info/METADATA
mosaiks-1.0.0.dist-info/WHEEL
mosaiks-1.0.0.dist-info/top_level.txt
mosaiks-1.0.0.dist-info/RECORD
