Metadata-Version: 2.1
Name: mosaiks
Version: 1.0.0
Summary: Use the MOSAIKS algorithm to create features from satellite imagery
Author: IDinsight
Keywords: satellite,mosaiks,geospatial
Requires-Python: >=3.9
License-File: LICENSE
Requires-Dist: torch ==2.0.1
Requires-Dist: numpy ==1.25.1
Requires-Dist: pandas ==2.0.3
Requires-Dist: matplotlib ==3.7.2
Requires-Dist: planetary-computer ==1.0.0
Requires-Dist: pystac-client ==0.7.2
Requires-Dist: stackstac ==0.4.4
Requires-Dist: dask ==2023.7.0
Requires-Dist: dask-gateway ==2023.1.1
Requires-Dist: bokeh ==3.2.0
Requires-Dist: geopandas ==0.13.2
Requires-Dist: dask-geopandas ==0.3.1
Requires-Dist: shapely ==2.0.1
Requires-Dist: pyproj ==3.6.0
Requires-Dist: pygeos ==0.14
Requires-Dist: pyarrow ==12.0.1
Requires-Dist: ipykernel ==6.24.0
